lite.py
lite-0.1.4.dist-info/WHEEL
lite-0.1.4.dist-info/METADATA
lite-0.1.4.dist-info/RECORD
